atlantic/__init__.py
atlantic/core/__init__.py
atlantic/core/base.py
atlantic/core/enums.py
atlantic/core/exceptions.py
atlantic/core/mixins.py
atlantic/core/schemas.py
atlantic/data/__init__.py
atlantic/data/generator.py
atlantic/encoding/__init__.py
atlantic/encoding/optimizer.py
atlantic/encoding/versions.py
atlantic/evaluation/__init__.py
atlantic/evaluation/metrics.py
atlantic/feature_selection/__init__.py
atlantic/feature_selection/h2o_selector.py
atlantic/feature_selection/registry.py
atlantic/feature_selection/vif_selector.py
atlantic/optimization/__init__.py
atlantic/optimization/base.py
atlantic/optimization/dimensionality.py
atlantic/optimization/evaluation.py
atlantic/optimization/optuna_adapter.py
atlantic/pipeline/__init__.py
atlantic/pipeline/atlantic.py
atlantic/pipeline/builder.py
atlantic/pipeline/pattern.py
atlantic/preprocessing/__init__.py
atlantic/preprocessing/base.py
atlantic/preprocessing/encoders.py
atlantic/preprocessing/imputers.py
atlantic/preprocessing/registry.py
atlantic/preprocessing/scalers.py
atlantic/state/__init__.py
atlantic/state/pipeline_state.py
atlantic/utils/__init__.py
atlantic/utils/columns.py
atlantic/utils/datetime.py
atlantic/utils/validation.py
atlantic-2.0.29.dist-info/licenses/LICENSE
atlantic-2.0.29.dist-info/METADATA
atlantic-2.0.29.dist-info/WHEEL
atlantic-2.0.29.dist-info/top_level.txt
atlantic-2.0.29.dist-info/RECORD
