Metadata-Version: 2.4
Name: atlantic
Version: 2.0.29
Summary: Atlantic is an automated preprocessing framework for supervised machine learning
Home-page: https://github.com/TsLu1s/Atlantic
Author: Luís Fernando da Silva Santos
Author-email: luisf_ssantos@hotmail.com
License: MIT
Keywords: data science,machine learning,data processing,predictive modeling,data preprocessing,automated data preprocessing,automated machine learning,automl
Classifier: Intended Audience :: Education
Classifier: Intended Audience :: Developers
Classifier: Intended Audience :: Science/Research
Classifier: Intended Audience :: Customer Service
Classifier: Intended Audience :: Financial and Insurance Industry
Classifier: Intended Audience :: Healthcare Industry
Classifier: Intended Audience :: Telecommunications Industry
Classifier: Topic :: Scientific/Engineering :: Artificial Intelligence
Classifier: Topic :: Scientific/Engineering :: Information Analysis
Classifier: License :: OSI Approved :: MIT License
Classifier: Operating System :: OS Independent
Classifier: Programming Language :: Python :: 3.10
Classifier: Programming Language :: Python :: 3.11
Classifier: Programming Language :: Python :: 3.12
License-File: LICENSE
Requires-Dist: pandas>=2.0.0
Requires-Dist: numpy>=1.24.0
Requires-Dist: scikit-learn>=1.4.0
Requires-Dist: h2o>=3.44.0.1
Requires-Dist: xgboost==2.0.3
Requires-Dist: optuna>=3.0.0
Requires-Dist: statsmodels>=0.14.0
Requires-Dist: pydantic>=2.0.0
Requires-Dist: tqdm>=4.60.0
Dynamic: author
Dynamic: author-email
Dynamic: classifier
Dynamic: description
Dynamic: description-content-type
Dynamic: home-page
Dynamic: keywords
Dynamic: license
Dynamic: license-file
Dynamic: requires-dist
Dynamic: summary
